dataproc/__init__.py
dataproc/cache.py
dataproc/clients/__init__.py
dataproc/clients/crawler.py
dataproc/clients/plasma_lib.py
dataproc/cmd/__init__.py
dataproc/cmd/feeds.py
dataproc/cmd/manager.py
dataproc/cmd/plasma.py
dataproc/cmd/site.py
dataproc/cmd/workflows.py
dataproc/conf.py
dataproc/crawlers/__init__.py
dataproc/crawlers/batch.py
dataproc/crawlers/batch_root.py
dataproc/crawlers/datastore.py
dataproc/crawlers/documents_index.py
dataproc/crawlers/fetcher.py
dataproc/crawlers/google.py
dataproc/crawlers/http_client.py
dataproc/crawlers/image.py
dataproc/crawlers/indexes.py
dataproc/crawlers/links_extractors.py
dataproc/crawlers/managers/__init__.py
dataproc/crawlers/managers/bucket.py
dataproc/crawlers/managers/data_task.py
dataproc/crawlers/managers/page.py
dataproc/crawlers/managers/site.py
dataproc/crawlers/models.py
dataproc/crawlers/page.py
dataproc/crawlers/parsers/__init__.py
dataproc/crawlers/parsers/article.py
dataproc/crawlers/parsers/authors.py
dataproc/crawlers/parsers/html.py
dataproc/crawlers/parsers/mppage.py
dataproc/crawlers/parsers/page.py
dataproc/crawlers/parsers/rss.py
dataproc/crawlers/parsers/sitexml.py
dataproc/crawlers/parsers/url.py
dataproc/crawlers/root.py
dataproc/crawlers/url_index.py
dataproc/crawlers/utils.py
dataproc/crawlers/web.py
dataproc/crawlers/youtube.py
dataproc/datasets/__init__.py
dataproc/datasets/dataset.py
dataproc/datasets/managers/dataset.py
dataproc/datasets/models.py
dataproc/datasets/table.py
dataproc/datasets/utils.py
dataproc/datastore/__init__.py
dataproc/datastore/base_model.py
dataproc/datastore/core.py
dataproc/datastore/managers.py
dataproc/hashes/generators.py
dataproc/hashes/newsid.py
dataproc/hashes/noncrypto.py
dataproc/hashes/objectid.py
dataproc/http_client.py
dataproc/regions/__init__.py
dataproc/regions/models.py
dataproc/regions/places.py
dataproc/server.py
dataproc/shortcuts.py
dataproc/social/__init__.py
dataproc/social/core.py
dataproc/social/google.py
dataproc/social/linkedin.py
ai_dataproc-0.1.0.dist-info/WHEEL
ai_dataproc-0.1.0.dist-info/METADATA
ai_dataproc-0.1.0.dist-info/RECORD
